kozmoai/__init__.py
kozmoai/assets/reference.json
kozmoai/py.typed
kozmoai_nightly-4.4.1.dev202506161451.dist-info/METADATA
kozmoai_nightly-4.4.1.dev202506161451.dist-info/WHEEL
kozmoai_nightly-4.4.1.dev202506161451.dist-info/RECORD
