Metadata-Version: 2.3
Name: kozmoai-nightly
Version: 4.4.1.dev202506161451
Summary: Investment research for everyone, anywhere.
License: AGPL-3.0-only
Author: KozmoAI Team
Author-email: hello@kozmoai.co
Requires-Python: >=3.9.21,<3.13
Classifier: License :: OSI Approved :: GNU Affero General Public License v3
Classifier: Programming Language :: Python :: 3
Classifier: Programming Language :: Python :: 3.10
Classifier: Programming Language :: Python :: 3.11
Classifier: Programming Language :: Python :: 3.12
Provides-Extra: all
Provides-Extra: alpha-vantage
Provides-Extra: biztoc
Provides-Extra: cboe
Provides-Extra: charting
Provides-Extra: ecb
Provides-Extra: econometrics
Provides-Extra: finra
Provides-Extra: finviz
Provides-Extra: government-us
Provides-Extra: multpl
Provides-Extra: nasdaq
Provides-Extra: quantitative
Provides-Extra: seeking-alpha
Provides-Extra: stockgrid
Provides-Extra: technical
Provides-Extra: tmx
Provides-Extra: tradier
Provides-Extra: wsj
Requires-Dist: kozmoai-alpha-vantage (>=1.4.0,<2.0.0) ; extra == "alpha-vantage" or extra == "all"
Requires-Dist: kozmoai-benzinga (>=1.4.0,<2.0.0)
Requires-Dist: kozmoai-biztoc (>=1.4.0,<2.0.0) ; extra == "biztoc" or extra == "all"
Requires-Dist: kozmoai-bls (>=1.1.0,<2.0.0)
Requires-Dist: kozmoai-cboe (>=1.4.0,<2.0.0) ; extra == "cboe" or extra == "all"
Requires-Dist: kozmoai-cftc (>=1.1.0,<2.0.0)
Requires-Dist: kozmoai-charting (>=2.3.2,<3.0.0) ; extra == "charting" or extra == "all"
Requires-Dist: kozmoai-commodity (>=1.3.0,<2.0.0)
Requires-Dist: kozmoai-core (>=1.4.2,<2.0.0)
Requires-Dist: kozmoai-crypto (>=1.4.0,<2.0.0)
Requires-Dist: kozmoai-currency (>=1.4.0,<2.0.0)
Requires-Dist: kozmoai-deribit (>=1.0.0,<2.0.0) ; extra == "all"
Requires-Dist: kozmoai-derivatives (>=1.4.0,<2.0.0)
Requires-Dist: kozmoai-ecb (>=1.4.1,<2.0.0) ; extra == "ecb" or extra == "all"
Requires-Dist: kozmoai-econdb (>=1.3.0,<2.0.0)
Requires-Dist: kozmoai-econometrics (>=1.5.1,<2.0.0) ; extra == "econometrics" or extra == "all"
Requires-Dist: kozmoai-economy (>=1.4.0,<2.0.0)
Requires-Dist: kozmoai-equity (>=1.4.0,<2.0.0)
Requires-Dist: kozmoai-etf (>=1.4.0,<2.0.0)
Requires-Dist: kozmoai-federal-reserve (>=1.4.0,<2.0.0)
Requires-Dist: kozmoai-finra (>=1.4.0,<2.0.0) ; extra == "finra" or extra == "all"
Requires-Dist: kozmoai-finviz (>=1.3.0,<2.0.0) ; extra == "finviz" or extra == "all"
Requires-Dist: kozmoai-fixedincome (>=1.4.2,<2.0.0)
Requires-Dist: kozmoai-fmp (>=1.4.1,<2.0.0)
Requires-Dist: kozmoai-fred (>=1.4.1,<2.0.0)
Requires-Dist: kozmoai-government-us (>=1.4.0,<2.0.0) ; extra == "government-us" or extra == "all"
Requires-Dist: kozmoai-imf (>=1.1.0,<2.0.0)
Requires-Dist: kozmoai-index (>=1.4.0,<2.0.0)
Requires-Dist: kozmoai-intrinio (>=1.4.0,<2.0.0)
Requires-Dist: kozmoai-multpl (>=1.1.0,<2.0.0) ; extra == "multpl" or extra == "all"
Requires-Dist: kozmoai-nasdaq (>=1.4.0,<2.0.0) ; extra == "nasdaq" or extra == "all"
Requires-Dist: kozmoai-news (>=1.4.0,<2.0.0)
Requires-Dist: kozmoai-oecd (>=1.4.0,<2.0.0)
Requires-Dist: kozmoai-platform-api (>=1.1.4,<2.0.0)
Requires-Dist: kozmoai-polygon (>=1.4.0,<2.0.0)
Requires-Dist: kozmoai-quantitative (>=1.4.1,<2.0.0) ; extra == "quantitative" or extra == "all"
Requires-Dist: kozmoai-regulators (>=1.4.1,<2.0.0)
Requires-Dist: kozmoai-sec (>=1.4.1,<2.0.0)
Requires-Dist: kozmoai-seeking-alpha (>=1.4.0,<2.0.0) ; extra == "seeking-alpha" or extra == "all"
Requires-Dist: kozmoai-stockgrid (>=1.4.0,<2.0.0) ; extra == "stockgrid" or extra == "all"
Requires-Dist: kozmoai-technical (>=1.4.1,<2.0.0) ; extra == "technical" or extra == "all"
Requires-Dist: kozmoai-tiingo (>=1.4.0,<2.0.0)
Requires-Dist: kozmoai-tmx (>=1.3.0,<2.0.0) ; extra == "tmx" or extra == "all"
Requires-Dist: kozmoai-tradier (>=1.3.0,<2.0.0) ; extra == "tradier" or extra == "all"
Requires-Dist: kozmoai-tradingeconomics (>=1.4.0,<2.0.0)
Requires-Dist: kozmoai-us-eia (>=1.1.0,<2.0.0)
Requires-Dist: kozmoai-wsj (>=1.4.0,<2.0.0) ; extra == "wsj" or extra == "all"
Requires-Dist: kozmoai-yfinance (>=1.4.1,<2.0.0)
